mwl_phonemizer/__init__.py
mwl_phonemizer/base.py
mwl_phonemizer/central.json
mwl_phonemizer/char_lookup_mwl.py
mwl_phonemizer/crf_epitran_mwl.py
mwl_phonemizer/crf_espeak_mwl.py
mwl_phonemizer/crf_mwl.py
mwl_phonemizer/crf_ortho_mwl.py
mwl_phonemizer/epitran_mwl.py
mwl_phonemizer/espeak_mwl.py
mwl_phonemizer/g2p.json
mwl_phonemizer/ngram_mwl.py
mwl_phonemizer/orthography_hand_rules.py
mwl_phonemizer/raiano.json
mwl_phonemizer/sendinese.json
mwl_phonemizer/version.py
mwl_phonemizer-0.0.4.dist-info/METADATA
mwl_phonemizer-0.0.4.dist-info/WHEEL
mwl_phonemizer-0.0.4.dist-info/top_level.txt
mwl_phonemizer-0.0.4.dist-info/RECORD
