Metadata-Version: 2.1
Name: mwl-phonemizer
Version: 0.0.4
Home-page: https://github.com/TigreGotico/mwl_phonemizer
Author: JarbasAi
Author-email: jarbasai@mailfence.com
Requires-Dist: python-Levenshtein
Requires-Dist: sklearn-crfsuite
